sertistssim/__init__.py
sertistssim/sertistssim.py
tests/__init__.py
tests/testcode.py
sertistssim-0.2.dist-info/LICENSE
sertistssim-0.2.dist-info/METADATA
sertistssim-0.2.dist-info/WHEEL
sertistssim-0.2.dist-info/top_level.txt
sertistssim-0.2.dist-info/RECORD
